Metadata-Version: 2.1
Name: e621-stable
Version: 1.0.4
Summary: e621.net API wrapper written in Python
Home-page: https://github.com/Hmiku8338/e621-py-stable
License: MIT
Keywords: e621.net,e621,e926.net,e926,furry,yiff,api,booru
Author: Hmiku8338
Author-email: hmiku8338@gmail.com
Requires-Python: >=3.7,<4.0
Classifier: License :: OSI Approved :: MIT License
Classifier: Operating System :: OS Independent
Classifier: Programming Language :: Python :: 3
Classifier: Programming Language :: Python :: 3.7
Classifier: Programming Language :: Python :: 3.8
Classifier: Programming Language :: Python :: 3.9
Classifier: Programming Language :: Python :: 3.10
Classifier: Programming Language :: Python :: 3.11
Requires-Dist: backports.cached-property (>=1.0.1,<2.0.0)
Requires-Dist: pydantic (>=1.9.0,<2.0.0)
Requires-Dist: requests (>=2.27.1,<3.0.0)
Requires-Dist: typing-extensions (>=4.1.1,<5.0.0)
Project-URL: Repository, https://github.com/Hmiku8338/e621-py-stable
